[
  {
    "line": 1,
    "type": "surah_name",
    "is_centered": true,
    "surah": 15,
    "words": []
  },
  {
    "line": 2,
    "type": "basmallah",
    "is_centered": true,
    "surah": "",
    "words": []
  },
  {
    "line": 3,
    "type": "ayah",
    "is_centered": false,
    "surah": "",
    "words": [
      {
        "c": "ﱁﱂ",
        "l": "15:1:1",
        "a": "1",
        "s": "15"
      },
      {
        "c": "ﱃ",
        "l": "15:1:2",
        "a": "1",
        "s": "15"
      },
      {
        "c": "ﱄ",
        "l": "15:1:3",
        "a": "1",
        "s": "15"
      },
      {
        "c": "ﱅ",
        "l": "15:1:4",
        "a": "1",
        "s": "15"
      },
      {
        "c": "ﱆ",
        "l": "15:1:5",
        "a": "1",
        "s": "15"
      },
      {
        "c": "ﱇ",
        "l": "15:1:6",
        "a": "1",
        "s": "15"
      },
      {
        "c": "ﱈ",
        "l": "15:1:7",
        "a": "1",
        "s": "15"
      },
      {
        "c": "ﱉ",
        "l": "15:2:1",
        "a": "2",
        "s": "15"
      },
      {
        "c": "ﱊ",
        "l": "15:2:2",
        "a": "2",
        "s": "15"
      }
    ]
  },
  {
    "line": 4,
    "type": "ayah",
    "is_centered": false,
    "surah": "",
    "words": [
      {
        "c": "ﱋ",
        "l": "15:2:3",
        "a": "2",
        "s": "15"
      },
      {
        "c": "ﱌ",
        "l": "15:2:4",
        "a": "2",
        "s": "15"
      },
      {
        "c": "ﱍ",
        "l": "15:2:5",
        "a": "2",
        "s": "15"
      },
      {
        "c": "ﱎ",
        "l": "15:2:6",
        "a": "2",
        "s": "15"
      },
      {
        "c": "ﱏ",
        "l": "15:2:7",
        "a": "2",
        "s": "15"
      },
      {
        "c": "ﱐ",
        "l": "15:2:8",
        "a": "2",
        "s": "15"
      },
      {
        "c": "ﱑ",
        "l": "15:3:1",
        "a": "3",
        "s": "15"
      },
      {
        "c": "ﱒ",
        "l": "15:3:2",
        "a": "3",
        "s": "15"
      }
    ]
  },
  {
    "line": 5,
    "type": "ayah",
    "is_centered": false,
    "surah": "",
    "words": [
      {
        "c": "ﱓ",
        "l": "15:3:3",
        "a": "3",
        "s": "15"
      },
      {
        "c": "ﱔ",
        "l": "15:3:4",
        "a": "3",
        "s": "15"
      },
      {
        "c": "ﱕﱖ",
        "l": "15:3:5",
        "a": "3",
        "s": "15"
      },
      {
        "c": "ﱗ",
        "l": "15:3:6",
        "a": "3",
        "s": "15"
      },
      {
        "c": "ﱘ",
        "l": "15:3:7",
        "a": "3",
        "s": "15"
      },
      {
        "c": "ﱙ",
        "l": "15:3:8",
        "a": "3",
        "s": "15"
      },
      {
        "c": "ﱚ",
        "l": "15:4:1",
        "a": "4",
        "s": "15"
      },
      {
        "c": "ﱛ",
        "l": "15:4:2",
        "a": "4",
        "s": "15"
      }
    ]
  },
  {
    "line": 6,
    "type": "ayah",
    "is_centered": false,
    "surah": "",
    "words": [
      {
        "c": "ﱜ",
        "l": "15:4:3",
        "a": "4",
        "s": "15"
      },
      {
        "c": "ﱝ",
        "l": "15:4:4",
        "a": "4",
        "s": "15"
      },
      {
        "c": "ﱞ",
        "l": "15:4:5",
        "a": "4",
        "s": "15"
      },
      {
        "c": "ﱟ",
        "l": "15:4:6",
        "a": "4",
        "s": "15"
      },
      {
        "c": "ﱠ",
        "l": "15:4:7",
        "a": "4",
        "s": "15"
      },
      {
        "c": "ﱡ",
        "l": "15:4:8",
        "a": "4",
        "s": "15"
      },
      {
        "c": "ﱢ",
        "l": "15:4:9",
        "a": "4",
        "s": "15"
      },
      {
        "c": "ﱣ",
        "l": "15:5:1",
        "a": "5",
        "s": "15"
      },
      {
        "c": "ﱤ",
        "l": "15:5:2",
        "a": "5",
        "s": "15"
      },
      {
        "c": "ﱥ",
        "l": "15:5:3",
        "a": "5",
        "s": "15"
      },
      {
        "c": "ﱦ",
        "l": "15:5:4",
        "a": "5",
        "s": "15"
      }
    ]
  },
  {
    "line": 7,
    "type": "ayah",
    "is_centered": false,
    "surah": "",
    "words": [
      {
        "c": "ﱧ",
        "l": "15:5:5",
        "a": "5",
        "s": "15"
      },
      {
        "c": "ﱨ",
        "l": "15:5:6",
        "a": "5",
        "s": "15"
      },
      {
        "c": "ﱩ",
        "l": "15:5:7",
        "a": "5",
        "s": "15"
      },
      {
        "c": "ﱪ",
        "l": "15:5:8",
        "a": "5",
        "s": "15"
      },
      {
        "c": "ﱫ",
        "l": "15:6:1",
        "a": "6",
        "s": "15"
      },
      {
        "c": "ﱬ",
        "l": "15:6:2",
        "a": "6",
        "s": "15"
      },
      {
        "c": "ﱭ",
        "l": "15:6:3",
        "a": "6",
        "s": "15"
      },
      {
        "c": "ﱮ",
        "l": "15:6:4",
        "a": "6",
        "s": "15"
      },
      {
        "c": "ﱯ",
        "l": "15:6:5",
        "a": "6",
        "s": "15"
      }
    ]
  },
  {
    "line": 8,
    "type": "ayah",
    "is_centered": false,
    "surah": "",
    "words": [
      {
        "c": "ﱰ",
        "l": "15:6:6",
        "a": "6",
        "s": "15"
      },
      {
        "c": "ﱱ",
        "l": "15:6:7",
        "a": "6",
        "s": "15"
      },
      {
        "c": "ﱲ",
        "l": "15:6:8",
        "a": "6",
        "s": "15"
      },
      {
        "c": "ﱳ",
        "l": "15:6:9",
        "a": "6",
        "s": "15"
      },
      {
        "c": "ﱴ",
        "l": "15:7:1",
        "a": "7",
        "s": "15"
      },
      {
        "c": "ﱵ",
        "l": "15:7:2",
        "a": "7",
        "s": "15"
      },
      {
        "c": "ﱶ",
        "l": "15:7:3",
        "a": "7",
        "s": "15"
      },
      {
        "c": "ﱷ",
        "l": "15:7:4",
        "a": "7",
        "s": "15"
      },
      {
        "c": "ﱸ",
        "l": "15:7:5",
        "a": "7",
        "s": "15"
      },
      {
        "c": "ﱹ",
        "l": "15:7:6",
        "a": "7",
        "s": "15"
      }
    ]
  },
  {
    "line": 9,
    "type": "ayah",
    "is_centered": false,
    "surah": "",
    "words": [
      {
        "c": "ﱺ",
        "l": "15:7:7",
        "a": "7",
        "s": "15"
      },
      {
        "c": "ﱻ",
        "l": "15:7:8",
        "a": "7",
        "s": "15"
      },
      {
        "c": "ﱼ",
        "l": "15:7:9",
        "a": "7",
        "s": "15"
      },
      {
        "c": "ﱽ",
        "l": "15:8:1",
        "a": "8",
        "s": "15"
      },
      {
        "c": "ﱾ",
        "l": "15:8:2",
        "a": "8",
        "s": "15"
      },
      {
        "c": "ﱿ",
        "l": "15:8:3",
        "a": "8",
        "s": "15"
      },
      {
        "c": "ﲀ",
        "l": "15:8:4",
        "a": "8",
        "s": "15"
      },
      {
        "c": "ﲁ",
        "l": "15:8:5",
        "a": "8",
        "s": "15"
      },
      {
        "c": "ﲂ",
        "l": "15:8:6",
        "a": "8",
        "s": "15"
      },
      {
        "c": "ﲃ",
        "l": "15:8:7",
        "a": "8",
        "s": "15"
      }
    ]
  },
  {
    "line": 10,
    "type": "ayah",
    "is_centered": false,
    "surah": "",
    "words": [
      {
        "c": "ﲄ",
        "l": "15:8:8",
        "a": "8",
        "s": "15"
      },
      {
        "c": "ﲅ",
        "l": "15:8:9",
        "a": "8",
        "s": "15"
      },
      {
        "c": "ﲆ",
        "l": "15:8:10",
        "a": "8",
        "s": "15"
      },
      {
        "c": "ﲇ",
        "l": "15:9:1",
        "a": "9",
        "s": "15"
      },
      {
        "c": "ﲈ",
        "l": "15:9:2",
        "a": "9",
        "s": "15"
      },
      {
        "c": "ﲉ",
        "l": "15:9:3",
        "a": "9",
        "s": "15"
      },
      {
        "c": "ﲊ",
        "l": "15:9:4",
        "a": "9",
        "s": "15"
      },
      {
        "c": "ﲋ",
        "l": "15:9:5",
        "a": "9",
        "s": "15"
      },
      {
        "c": "ﲌ",
        "l": "15:9:6",
        "a": "9",
        "s": "15"
      },
      {
        "c": "ﲍ",
        "l": "15:9:7",
        "a": "9",
        "s": "15"
      },
      {
        "c": "ﲎ",
        "l": "15:9:8",
        "a": "9",
        "s": "15"
      }
    ]
  },
  {
    "line": 11,
    "type": "ayah",
    "is_centered": false,
    "surah": "",
    "words": [
      {
        "c": "ﲏ",
        "l": "15:10:1",
        "a": "10",
        "s": "15"
      },
      {
        "c": "ﲐ",
        "l": "15:10:2",
        "a": "10",
        "s": "15"
      },
      {
        "c": "ﲑ",
        "l": "15:10:3",
        "a": "10",
        "s": "15"
      },
      {
        "c": "ﲒ",
        "l": "15:10:4",
        "a": "10",
        "s": "15"
      },
      {
        "c": "ﲓ",
        "l": "15:10:5",
        "a": "10",
        "s": "15"
      },
      {
        "c": "ﲔ",
        "l": "15:10:6",
        "a": "10",
        "s": "15"
      },
      {
        "c": "ﲕ",
        "l": "15:10:7",
        "a": "10",
        "s": "15"
      },
      {
        "c": "ﲖ",
        "l": "15:10:8",
        "a": "10",
        "s": "15"
      },
      {
        "c": "ﲗ",
        "l": "15:11:1",
        "a": "11",
        "s": "15"
      },
      {
        "c": "ﲘ",
        "l": "15:11:2",
        "a": "11",
        "s": "15"
      }
    ]
  },
  {
    "line": 12,
    "type": "ayah",
    "is_centered": false,
    "surah": "",
    "words": [
      {
        "c": "ﲙ",
        "l": "15:11:3",
        "a": "11",
        "s": "15"
      },
      {
        "c": "ﲚ",
        "l": "15:11:4",
        "a": "11",
        "s": "15"
      },
      {
        "c": "ﲛ",
        "l": "15:11:5",
        "a": "11",
        "s": "15"
      },
      {
        "c": "ﲜ",
        "l": "15:11:6",
        "a": "11",
        "s": "15"
      },
      {
        "c": "ﲝ",
        "l": "15:11:7",
        "a": "11",
        "s": "15"
      },
      {
        "c": "ﲞ",
        "l": "15:11:8",
        "a": "11",
        "s": "15"
      },
      {
        "c": "ﲟ",
        "l": "15:11:9",
        "a": "11",
        "s": "15"
      },
      {
        "c": "ﲠ",
        "l": "15:12:1",
        "a": "12",
        "s": "15"
      },
      {
        "c": "ﲡ",
        "l": "15:12:2",
        "a": "12",
        "s": "15"
      }
    ]
  },
  {
    "line": 13,
    "type": "ayah",
    "is_centered": false,
    "surah": "",
    "words": [
      {
        "c": "ﲢ",
        "l": "15:12:3",
        "a": "12",
        "s": "15"
      },
      {
        "c": "ﲣ",
        "l": "15:12:4",
        "a": "12",
        "s": "15"
      },
      {
        "c": "ﲤ",
        "l": "15:12:5",
        "a": "12",
        "s": "15"
      },
      {
        "c": "ﲥ",
        "l": "15:12:6",
        "a": "12",
        "s": "15"
      },
      {
        "c": "ﲦ",
        "l": "15:13:1",
        "a": "13",
        "s": "15"
      },
      {
        "c": "ﲧ",
        "l": "15:13:2",
        "a": "13",
        "s": "15"
      },
      {
        "c": "ﲨ",
        "l": "15:13:3",
        "a": "13",
        "s": "15"
      },
      {
        "c": "ﲩ",
        "l": "15:13:4",
        "a": "13",
        "s": "15"
      },
      {
        "c": "ﲪ",
        "l": "15:13:5",
        "a": "13",
        "s": "15"
      },
      {
        "c": "ﲫ",
        "l": "15:13:6",
        "a": "13",
        "s": "15"
      },
      {
        "c": "ﲬ",
        "l": "15:13:7",
        "a": "13",
        "s": "15"
      }
    ]
  },
  {
    "line": 14,
    "type": "ayah",
    "is_centered": false,
    "surah": "",
    "words": [
      {
        "c": "ﲭ",
        "l": "15:13:8",
        "a": "13",
        "s": "15"
      },
      {
        "c": "ﲮ",
        "l": "15:14:1",
        "a": "14",
        "s": "15"
      },
      {
        "c": "ﲯ",
        "l": "15:14:2",
        "a": "14",
        "s": "15"
      },
      {
        "c": "ﲰ",
        "l": "15:14:3",
        "a": "14",
        "s": "15"
      },
      {
        "c": "ﲱ",
        "l": "15:14:4",
        "a": "14",
        "s": "15"
      },
      {
        "c": "ﲲ",
        "l": "15:14:5",
        "a": "14",
        "s": "15"
      },
      {
        "c": "ﲳ",
        "l": "15:14:6",
        "a": "14",
        "s": "15"
      },
      {
        "c": "ﲴ",
        "l": "15:14:7",
        "a": "14",
        "s": "15"
      },
      {
        "c": "ﲵ",
        "l": "15:14:8",
        "a": "14",
        "s": "15"
      },
      {
        "c": "ﲶ",
        "l": "15:14:9",
        "a": "14",
        "s": "15"
      },
      {
        "c": "ﲷ",
        "l": "15:14:10",
        "a": "14",
        "s": "15"
      }
    ]
  },
  {
    "line": 15,
    "type": "ayah",
    "is_centered": false,
    "surah": "",
    "words": [
      {
        "c": "ﲸ",
        "l": "15:15:1",
        "a": "15",
        "s": "15"
      },
      {
        "c": "ﲹ",
        "l": "15:15:2",
        "a": "15",
        "s": "15"
      },
      {
        "c": "ﲺ",
        "l": "15:15:3",
        "a": "15",
        "s": "15"
      },
      {
        "c": "ﲻ",
        "l": "15:15:4",
        "a": "15",
        "s": "15"
      },
      {
        "c": "ﲼ",
        "l": "15:15:5",
        "a": "15",
        "s": "15"
      },
      {
        "c": "ﲽ",
        "l": "15:15:6",
        "a": "15",
        "s": "15"
      },
      {
        "c": "ﲾ",
        "l": "15:15:7",
        "a": "15",
        "s": "15"
      },
      {
        "c": "ﲿ",
        "l": "15:15:8",
        "a": "15",
        "s": "15"
      },
      {
        "c": "ﳀ",
        "l": "15:15:9",
        "a": "15",
        "s": "15"
      }
    ]
  }
]