[
  {
    "line": 1,
    "type": "ayah",
    "is_centered": false,
    "surah": "",
    "words": [
      {
        "c": "ﱁ",
        "l": "21:91:1",
        "a": "91",
        "s": "21",
        "isStopSign": false
      },
      {
        "c": "ﱂ",
        "l": "21:91:2",
        "a": "91",
        "s": "21",
        "isStopSign": false
      },
      {
        "c": "ﱃ",
        "l": "21:91:3",
        "a": "91",
        "s": "21",
        "isStopSign": false
      },
      {
        "c": "ﱄ",
        "l": "21:91:4",
        "a": "91",
        "s": "21",
        "isStopSign": false
      },
      {
        "c": "ﱅ",
        "l": "21:91:5",
        "a": "91",
        "s": "21",
        "isStopSign": false
      },
      {
        "c": "ﱆ",
        "l": "21:91:6",
        "a": "91",
        "s": "21",
        "isStopSign": false
      },
      {
        "c": "ﱇ",
        "l": "21:91:7",
        "a": "91",
        "s": "21",
        "isStopSign": false
      }
    ]
  },
  {
    "line": 2,
    "type": "ayah",
    "is_centered": false,
    "surah": "",
    "words": [
      {
        "c": "ﱈ",
        "l": "21:91:8",
        "a": "91",
        "s": "21",
        "isStopSign": false
      },
      {
        "c": "ﱉ",
        "l": "21:91:9",
        "a": "91",
        "s": "21",
        "isStopSign": false
      },
      {
        "c": "ﱊ",
        "l": "21:91:10",
        "a": "91",
        "s": "21",
        "isStopSign": false
      },
      {
        "c": "ﱋ",
        "l": "21:91:11",
        "a": "91",
        "s": "21",
        "isStopSign": false
      },
      {
        "c": "ﱌ",
        "l": "21:91:12",
        "a": "91",
        "s": "21",
        "isStopSign": true
      },
      {
        "c": "ﱍ",
        "l": "21:92:1",
        "a": "92",
        "s": "21",
        "isStopSign": false
      },
      {
        "c": "ﱎ",
        "l": "21:92:2",
        "a": "92",
        "s": "21",
        "isStopSign": false
      }
    ]
  },
  {
    "line": 3,
    "type": "ayah",
    "is_centered": false,
    "surah": "",
    "words": [
      {
        "c": "ﱏ",
        "l": "21:92:3",
        "a": "92",
        "s": "21",
        "isStopSign": false
      },
      {
        "c": "ﱐ",
        "l": "21:92:4",
        "a": "92",
        "s": "21",
        "isStopSign": false
      },
      {
        "c": "ﱑ",
        "l": "21:92:5",
        "a": "92",
        "s": "21",
        "isStopSign": false
      },
      {
        "c": "ﱒ",
        "l": "21:92:6",
        "a": "92",
        "s": "21",
        "isStopSign": false
      },
      {
        "c": "ﱓ",
        "l": "21:92:7",
        "a": "92",
        "s": "21",
        "isStopSign": false
      },
      {
        "c": "ﱔ",
        "l": "21:92:8",
        "a": "92",
        "s": "21",
        "isStopSign": false
      },
      {
        "c": "ﱕ",
        "l": "21:92:9",
        "a": "92",
        "s": "21",
        "isStopSign": true
      }
    ]
  },
  {
    "line": 4,
    "type": "ayah",
    "is_centered": false,
    "surah": "",
    "words": [
      {
        "c": "ﱖ",
        "l": "21:93:1",
        "a": "93",
        "s": "21",
        "isStopSign": false
      },
      {
        "c": "ﱗ",
        "l": "21:93:2",
        "a": "93",
        "s": "21",
        "isStopSign": false
      },
      {
        "c": "ﱘﱙ",
        "l": "21:93:3",
        "a": "93",
        "s": "21",
        "isStopSign": false
      },
      {
        "c": "ﱚ",
        "l": "21:93:4",
        "a": "93",
        "s": "21",
        "isStopSign": false
      },
      {
        "c": "ﱛ",
        "l": "21:93:5",
        "a": "93",
        "s": "21",
        "isStopSign": false
      },
      {
        "c": "ﱜ",
        "l": "21:93:6",
        "a": "93",
        "s": "21",
        "isStopSign": false
      },
      {
        "c": "ﱝ",
        "l": "21:93:7",
        "a": "93",
        "s": "21",
        "isStopSign": true
      }
    ]
  },
  {
    "line": 5,
    "type": "ayah",
    "is_centered": false,
    "surah": "",
    "words": [
      {
        "c": "ﱞ",
        "l": "21:94:1",
        "a": "94",
        "s": "21",
        "isStopSign": false
      },
      {
        "c": "ﱟ",
        "l": "21:94:2",
        "a": "94",
        "s": "21",
        "isStopSign": false
      },
      {
        "c": "ﱠ",
        "l": "21:94:3",
        "a": "94",
        "s": "21",
        "isStopSign": false
      },
      {
        "c": "ﱡ",
        "l": "21:94:4",
        "a": "94",
        "s": "21",
        "isStopSign": false
      },
      {
        "c": "ﱢ",
        "l": "21:94:5",
        "a": "94",
        "s": "21",
        "isStopSign": false
      },
      {
        "c": "ﱣ",
        "l": "21:94:6",
        "a": "94",
        "s": "21",
        "isStopSign": false
      },
      {
        "c": "ﱤ",
        "l": "21:94:7",
        "a": "94",
        "s": "21",
        "isStopSign": false
      },
      {
        "c": "ﱥ",
        "l": "21:94:8",
        "a": "94",
        "s": "21",
        "isStopSign": false
      }
    ]
  },
  {
    "line": 6,
    "type": "ayah",
    "is_centered": false,
    "surah": "",
    "words": [
      {
        "c": "ﱦ",
        "l": "21:94:9",
        "a": "94",
        "s": "21",
        "isStopSign": false
      },
      {
        "c": "ﱧ",
        "l": "21:94:10",
        "a": "94",
        "s": "21",
        "isStopSign": false
      },
      {
        "c": "ﱨ",
        "l": "21:94:11",
        "a": "94",
        "s": "21",
        "isStopSign": false
      },
      {
        "c": "ﱩ",
        "l": "21:94:12",
        "a": "94",
        "s": "21",
        "isStopSign": false
      },
      {
        "c": "ﱪ",
        "l": "21:94:13",
        "a": "94",
        "s": "21",
        "isStopSign": true
      },
      {
        "c": "ﱫ",
        "l": "21:95:1",
        "a": "95",
        "s": "21",
        "isStopSign": false
      },
      {
        "c": "ﱬ",
        "l": "21:95:2",
        "a": "95",
        "s": "21",
        "isStopSign": false
      },
      {
        "c": "ﱭ",
        "l": "21:95:3",
        "a": "95",
        "s": "21",
        "isStopSign": false
      }
    ]
  },
  {
    "line": 7,
    "type": "ayah",
    "is_centered": false,
    "surah": "",
    "words": [
      {
        "c": "ﱮ",
        "l": "21:95:4",
        "a": "95",
        "s": "21",
        "isStopSign": false
      },
      {
        "c": "ﱯ",
        "l": "21:95:5",
        "a": "95",
        "s": "21",
        "isStopSign": false
      },
      {
        "c": "ﱰ",
        "l": "21:95:6",
        "a": "95",
        "s": "21",
        "isStopSign": false
      },
      {
        "c": "ﱱ",
        "l": "21:95:7",
        "a": "95",
        "s": "21",
        "isStopSign": false
      },
      {
        "c": "ﱲ",
        "l": "21:95:8",
        "a": "95",
        "s": "21",
        "isStopSign": true
      },
      {
        "c": "ﱳ",
        "l": "21:96:1",
        "a": "96",
        "s": "21",
        "isStopSign": false
      },
      {
        "c": "ﱴ",
        "l": "21:96:2",
        "a": "96",
        "s": "21",
        "isStopSign": false
      },
      {
        "c": "ﱵ",
        "l": "21:96:3",
        "a": "96",
        "s": "21",
        "isStopSign": false
      }
    ]
  },
  {
    "line": 8,
    "type": "ayah",
    "is_centered": false,
    "surah": "",
    "words": [
      {
        "c": "ﱶ",
        "l": "21:96:4",
        "a": "96",
        "s": "21",
        "isStopSign": false
      },
      {
        "c": "ﱷ",
        "l": "21:96:5",
        "a": "96",
        "s": "21",
        "isStopSign": false
      },
      {
        "c": "ﱸ",
        "l": "21:96:6",
        "a": "96",
        "s": "21",
        "isStopSign": false
      },
      {
        "c": "ﱹ",
        "l": "21:96:7",
        "a": "96",
        "s": "21",
        "isStopSign": false
      },
      {
        "c": "ﱺ",
        "l": "21:96:8",
        "a": "96",
        "s": "21",
        "isStopSign": false
      },
      {
        "c": "ﱻ",
        "l": "21:96:9",
        "a": "96",
        "s": "21",
        "isStopSign": false
      },
      {
        "c": "ﱼ",
        "l": "21:96:10",
        "a": "96",
        "s": "21",
        "isStopSign": false
      },
      {
        "c": "ﱽ",
        "l": "21:96:11",
        "a": "96",
        "s": "21",
        "isStopSign": true
      }
    ]
  },
  {
    "line": 9,
    "type": "ayah",
    "is_centered": false,
    "surah": "",
    "words": [
      {
        "c": "ﱾ",
        "l": "21:97:1",
        "a": "97",
        "s": "21",
        "isStopSign": false
      },
      {
        "c": "ﱿ",
        "l": "21:97:2",
        "a": "97",
        "s": "21",
        "isStopSign": false
      },
      {
        "c": "ﲀ",
        "l": "21:97:3",
        "a": "97",
        "s": "21",
        "isStopSign": false
      },
      {
        "c": "ﲁ",
        "l": "21:97:4",
        "a": "97",
        "s": "21",
        "isStopSign": false
      },
      {
        "c": "ﲂ",
        "l": "21:97:5",
        "a": "97",
        "s": "21",
        "isStopSign": false
      },
      {
        "c": "ﲃ",
        "l": "21:97:6",
        "a": "97",
        "s": "21",
        "isStopSign": false
      },
      {
        "c": "ﲄ",
        "l": "21:97:7",
        "a": "97",
        "s": "21",
        "isStopSign": false
      },
      {
        "c": "ﲅ",
        "l": "21:97:8",
        "a": "97",
        "s": "21",
        "isStopSign": false
      }
    ]
  },
  {
    "line": 10,
    "type": "ayah",
    "is_centered": false,
    "surah": "",
    "words": [
      {
        "c": "ﲆ",
        "l": "21:97:9",
        "a": "97",
        "s": "21",
        "isStopSign": false
      },
      {
        "c": "ﲇ",
        "l": "21:97:10",
        "a": "97",
        "s": "21",
        "isStopSign": false
      },
      {
        "c": "ﲈ",
        "l": "21:97:11",
        "a": "97",
        "s": "21",
        "isStopSign": false
      },
      {
        "c": "ﲉ",
        "l": "21:97:12",
        "a": "97",
        "s": "21",
        "isStopSign": false
      },
      {
        "c": "ﲊ",
        "l": "21:97:13",
        "a": "97",
        "s": "21",
        "isStopSign": false
      },
      {
        "c": "ﲋ",
        "l": "21:97:14",
        "a": "97",
        "s": "21",
        "isStopSign": false
      },
      {
        "c": "ﲌ",
        "l": "21:97:15",
        "a": "97",
        "s": "21",
        "isStopSign": false
      },
      {
        "c": "ﲍ",
        "l": "21:97:16",
        "a": "97",
        "s": "21",
        "isStopSign": false
      },
      {
        "c": "ﲎ",
        "l": "21:97:17",
        "a": "97",
        "s": "21",
        "isStopSign": false
      },
      {
        "c": "ﲏ",
        "l": "21:97:18",
        "a": "97",
        "s": "21",
        "isStopSign": false
      }
    ]
  },
  {
    "line": 11,
    "type": "ayah",
    "is_centered": false,
    "surah": "",
    "words": [
      {
        "c": "ﲐ",
        "l": "21:97:19",
        "a": "97",
        "s": "21",
        "isStopSign": false
      },
      {
        "c": "ﲑ",
        "l": "21:97:20",
        "a": "97",
        "s": "21",
        "isStopSign": true
      },
      {
        "c": "ﲒ",
        "l": "21:98:1",
        "a": "98",
        "s": "21",
        "isStopSign": false
      },
      {
        "c": "ﲓ",
        "l": "21:98:2",
        "a": "98",
        "s": "21",
        "isStopSign": false
      },
      {
        "c": "ﲔ",
        "l": "21:98:3",
        "a": "98",
        "s": "21",
        "isStopSign": false
      },
      {
        "c": "ﲕ",
        "l": "21:98:4",
        "a": "98",
        "s": "21",
        "isStopSign": false
      },
      {
        "c": "ﲖ",
        "l": "21:98:5",
        "a": "98",
        "s": "21",
        "isStopSign": false
      },
      {
        "c": "ﲗ",
        "l": "21:98:6",
        "a": "98",
        "s": "21",
        "isStopSign": false
      }
    ]
  },
  {
    "line": 12,
    "type": "ayah",
    "is_centered": false,
    "surah": "",
    "words": [
      {
        "c": "ﲘ",
        "l": "21:98:7",
        "a": "98",
        "s": "21",
        "isStopSign": false
      },
      {
        "c": "ﲙ",
        "l": "21:98:8",
        "a": "98",
        "s": "21",
        "isStopSign": false
      },
      {
        "c": "ﲚ",
        "l": "21:98:9",
        "a": "98",
        "s": "21",
        "isStopSign": false
      },
      {
        "c": "ﲛ",
        "l": "21:98:10",
        "a": "98",
        "s": "21",
        "isStopSign": false
      },
      {
        "c": "ﲜ",
        "l": "21:98:11",
        "a": "98",
        "s": "21",
        "isStopSign": false
      },
      {
        "c": "ﲝ",
        "l": "21:98:12",
        "a": "98",
        "s": "21",
        "isStopSign": true
      },
      {
        "c": "ﲞ",
        "l": "21:99:1",
        "a": "99",
        "s": "21",
        "isStopSign": false
      },
      {
        "c": "ﲟ",
        "l": "21:99:2",
        "a": "99",
        "s": "21",
        "isStopSign": false
      }
    ]
  },
  {
    "line": 13,
    "type": "ayah",
    "is_centered": false,
    "surah": "",
    "words": [
      {
        "c": "ﲠ",
        "l": "21:99:3",
        "a": "99",
        "s": "21",
        "isStopSign": false
      },
      {
        "c": "ﲡ",
        "l": "21:99:4",
        "a": "99",
        "s": "21",
        "isStopSign": false
      },
      {
        "c": "ﲢ",
        "l": "21:99:5",
        "a": "99",
        "s": "21",
        "isStopSign": false
      },
      {
        "c": "ﲣﲤ",
        "l": "21:99:6",
        "a": "99",
        "s": "21",
        "isStopSign": false
      },
      {
        "c": "ﲥ",
        "l": "21:99:7",
        "a": "99",
        "s": "21",
        "isStopSign": false
      },
      {
        "c": "ﲦ",
        "l": "21:99:8",
        "a": "99",
        "s": "21",
        "isStopSign": false
      },
      {
        "c": "ﲧ",
        "l": "21:99:9",
        "a": "99",
        "s": "21",
        "isStopSign": false
      },
      {
        "c": "ﲨ",
        "l": "21:99:10",
        "a": "99",
        "s": "21",
        "isStopSign": true
      }
    ]
  },
  {
    "line": 14,
    "type": "ayah",
    "is_centered": false,
    "surah": "",
    "words": [
      {
        "c": "ﲩ",
        "l": "21:100:1",
        "a": "100",
        "s": "21",
        "isStopSign": false
      },
      {
        "c": "ﲪ",
        "l": "21:100:2",
        "a": "100",
        "s": "21",
        "isStopSign": false
      },
      {
        "c": "ﲫ",
        "l": "21:100:3",
        "a": "100",
        "s": "21",
        "isStopSign": false
      },
      {
        "c": "ﲬ",
        "l": "21:100:4",
        "a": "100",
        "s": "21",
        "isStopSign": false
      },
      {
        "c": "ﲭ",
        "l": "21:100:5",
        "a": "100",
        "s": "21",
        "isStopSign": false
      },
      {
        "c": "ﲮ",
        "l": "21:100:6",
        "a": "100",
        "s": "21",
        "isStopSign": false
      },
      {
        "c": "ﲯ",
        "l": "21:100:7",
        "a": "100",
        "s": "21",
        "isStopSign": false
      },
      {
        "c": "ﲰ",
        "l": "21:100:8",
        "a": "100",
        "s": "21",
        "isStopSign": true
      },
      {
        "c": "ﲱ",
        "l": "21:101:1",
        "a": "101",
        "s": "21",
        "isStopSign": false
      },
      {
        "c": "ﲲ",
        "l": "21:101:2",
        "a": "101",
        "s": "21",
        "isStopSign": false
      }
    ]
  },
  {
    "line": 15,
    "type": "ayah",
    "is_centered": false,
    "surah": "",
    "words": [
      {
        "c": "ﲳ",
        "l": "21:101:3",
        "a": "101",
        "s": "21",
        "isStopSign": false
      },
      {
        "c": "ﲴ",
        "l": "21:101:4",
        "a": "101",
        "s": "21",
        "isStopSign": false
      },
      {
        "c": "ﲵ",
        "l": "21:101:5",
        "a": "101",
        "s": "21",
        "isStopSign": false
      },
      {
        "c": "ﲶ",
        "l": "21:101:6",
        "a": "101",
        "s": "21",
        "isStopSign": false
      },
      {
        "c": "ﲷ",
        "l": "21:101:7",
        "a": "101",
        "s": "21",
        "isStopSign": false
      },
      {
        "c": "ﲸ",
        "l": "21:101:8",
        "a": "101",
        "s": "21",
        "isStopSign": false
      },
      {
        "c": "ﲹ",
        "l": "21:101:9",
        "a": "101",
        "s": "21",
        "isStopSign": false
      },
      {
        "c": "ﲺ",
        "l": "21:101:10",
        "a": "101",
        "s": "21",
        "isStopSign": true
      }
    ]
  }
]