[
  {
    "line": 1,
    "type": "ayah",
    "is_centered": false,
    "surah": "",
    "words": [
      {
        "c": "ﱁ",
        "l": "57:25:1",
        "a": "25",
        "s": "57"
      },
      {
        "c": "ﱂ",
        "l": "57:25:2",
        "a": "25",
        "s": "57"
      },
      {
        "c": "ﱃ",
        "l": "57:25:3",
        "a": "25",
        "s": "57"
      },
      {
        "c": "ﱄ",
        "l": "57:25:4",
        "a": "25",
        "s": "57"
      },
      {
        "c": "ﱅ",
        "l": "57:25:5",
        "a": "25",
        "s": "57"
      },
      {
        "c": "ﱆ",
        "l": "57:25:6",
        "a": "25",
        "s": "57"
      },
      {
        "c": "ﱇ",
        "l": "57:25:7",
        "a": "25",
        "s": "57"
      }
    ]
  },
  {
    "line": 2,
    "type": "ayah",
    "is_centered": false,
    "surah": "",
    "words": [
      {
        "c": "ﱈ",
        "l": "57:25:8",
        "a": "25",
        "s": "57"
      },
      {
        "c": "ﱉ",
        "l": "57:25:9",
        "a": "25",
        "s": "57"
      },
      {
        "c": "ﱊ",
        "l": "57:25:10",
        "a": "25",
        "s": "57"
      },
      {
        "c": "ﱋﱌ",
        "l": "57:25:11",
        "a": "25",
        "s": "57"
      },
      {
        "c": "ﱍ",
        "l": "57:25:12",
        "a": "25",
        "s": "57"
      },
      {
        "c": "ﱎ",
        "l": "57:25:13",
        "a": "25",
        "s": "57"
      },
      {
        "c": "ﱏ",
        "l": "57:25:14",
        "a": "25",
        "s": "57"
      }
    ]
  },
  {
    "line": 3,
    "type": "ayah",
    "is_centered": false,
    "surah": "",
    "words": [
      {
        "c": "ﱐ",
        "l": "57:25:15",
        "a": "25",
        "s": "57"
      },
      {
        "c": "ﱑ",
        "l": "57:25:16",
        "a": "25",
        "s": "57"
      },
      {
        "c": "ﱒ",
        "l": "57:25:17",
        "a": "25",
        "s": "57"
      },
      {
        "c": "ﱓ",
        "l": "57:25:18",
        "a": "25",
        "s": "57"
      },
      {
        "c": "ﱔ",
        "l": "57:25:19",
        "a": "25",
        "s": "57"
      },
      {
        "c": "ﱕ",
        "l": "57:25:20",
        "a": "25",
        "s": "57"
      },
      {
        "c": "ﱖ",
        "l": "57:25:21",
        "a": "25",
        "s": "57"
      },
      {
        "c": "ﱗ",
        "l": "57:25:22",
        "a": "25",
        "s": "57"
      },
      {
        "c": "ﱘ",
        "l": "57:25:23",
        "a": "25",
        "s": "57"
      }
    ]
  },
  {
    "line": 4,
    "type": "ayah",
    "is_centered": false,
    "surah": "",
    "words": [
      {
        "c": "ﱙﱚ",
        "l": "57:25:24",
        "a": "25",
        "s": "57"
      },
      {
        "c": "ﱛ",
        "l": "57:25:25",
        "a": "25",
        "s": "57"
      },
      {
        "c": "ﱜ",
        "l": "57:25:26",
        "a": "25",
        "s": "57"
      },
      {
        "c": "ﱝ",
        "l": "57:25:27",
        "a": "25",
        "s": "57"
      },
      {
        "c": "ﱞ",
        "l": "57:25:28",
        "a": "25",
        "s": "57"
      },
      {
        "c": "ﱟ",
        "l": "57:25:29",
        "a": "25",
        "s": "57"
      },
      {
        "c": "ﱠ",
        "l": "57:26:1",
        "a": "26",
        "s": "57"
      },
      {
        "c": "ﱡ",
        "l": "57:26:2",
        "a": "26",
        "s": "57"
      },
      {
        "c": "ﱢ",
        "l": "57:26:3",
        "a": "26",
        "s": "57"
      },
      {
        "c": "ﱣ",
        "l": "57:26:4",
        "a": "26",
        "s": "57"
      }
    ]
  },
  {
    "line": 5,
    "type": "ayah",
    "is_centered": false,
    "surah": "",
    "words": [
      {
        "c": "ﱤ",
        "l": "57:26:5",
        "a": "26",
        "s": "57"
      },
      {
        "c": "ﱥ",
        "l": "57:26:6",
        "a": "26",
        "s": "57"
      },
      {
        "c": "ﱦ",
        "l": "57:26:7",
        "a": "26",
        "s": "57"
      },
      {
        "c": "ﱧ",
        "l": "57:26:8",
        "a": "26",
        "s": "57"
      },
      {
        "c": "ﱨﱩ",
        "l": "57:26:9",
        "a": "26",
        "s": "57"
      },
      {
        "c": "ﱪ",
        "l": "57:26:10",
        "a": "26",
        "s": "57"
      },
      {
        "c": "ﱫﱬ",
        "l": "57:26:11",
        "a": "26",
        "s": "57"
      }
    ]
  },
  {
    "line": 6,
    "type": "ayah",
    "is_centered": false,
    "surah": "",
    "words": [
      {
        "c": "ﱭ",
        "l": "57:26:12",
        "a": "26",
        "s": "57"
      },
      {
        "c": "ﱮ",
        "l": "57:26:13",
        "a": "26",
        "s": "57"
      },
      {
        "c": "ﱯ",
        "l": "57:26:14",
        "a": "26",
        "s": "57"
      },
      {
        "c": "ﱰ",
        "l": "57:26:15",
        "a": "26",
        "s": "57"
      },
      {
        "c": "ﱱ",
        "l": "57:27:1",
        "a": "27",
        "s": "57"
      },
      {
        "c": "ﱲ",
        "l": "57:27:2",
        "a": "27",
        "s": "57"
      },
      {
        "c": "ﱳ",
        "l": "57:27:3",
        "a": "27",
        "s": "57"
      },
      {
        "c": "ﱴ",
        "l": "57:27:4",
        "a": "27",
        "s": "57"
      }
    ]
  },
  {
    "line": 7,
    "type": "ayah",
    "is_centered": false,
    "surah": "",
    "words": [
      {
        "c": "ﱵ",
        "l": "57:27:5",
        "a": "27",
        "s": "57"
      },
      {
        "c": "ﱶ",
        "l": "57:27:6",
        "a": "27",
        "s": "57"
      },
      {
        "c": "ﱷ",
        "l": "57:27:7",
        "a": "27",
        "s": "57"
      },
      {
        "c": "ﱸ",
        "l": "57:27:8",
        "a": "27",
        "s": "57"
      },
      {
        "c": "ﱹ",
        "l": "57:27:9",
        "a": "27",
        "s": "57"
      },
      {
        "c": "ﱺ",
        "l": "57:27:10",
        "a": "27",
        "s": "57"
      },
      {
        "c": "ﱻﱼ",
        "l": "57:27:11",
        "a": "27",
        "s": "57"
      },
      {
        "c": "ﱽ",
        "l": "57:27:12",
        "a": "27",
        "s": "57"
      }
    ]
  },
  {
    "line": 8,
    "type": "ayah",
    "is_centered": false,
    "surah": "",
    "words": [
      {
        "c": "ﱾ",
        "l": "57:27:13",
        "a": "27",
        "s": "57"
      },
      {
        "c": "ﱿ",
        "l": "57:27:14",
        "a": "27",
        "s": "57"
      },
      {
        "c": "ﲀ",
        "l": "57:27:15",
        "a": "27",
        "s": "57"
      },
      {
        "c": "ﲁ",
        "l": "57:27:16",
        "a": "27",
        "s": "57"
      },
      {
        "c": "ﲂ",
        "l": "57:27:17",
        "a": "27",
        "s": "57"
      },
      {
        "c": "ﲃﲄ",
        "l": "57:27:18",
        "a": "27",
        "s": "57"
      },
      {
        "c": "ﲅ",
        "l": "57:27:19",
        "a": "27",
        "s": "57"
      }
    ]
  },
  {
    "line": 9,
    "type": "ayah",
    "is_centered": false,
    "surah": "",
    "words": [
      {
        "c": "ﲆ",
        "l": "57:27:20",
        "a": "27",
        "s": "57"
      },
      {
        "c": "ﲇ",
        "l": "57:27:21",
        "a": "27",
        "s": "57"
      },
      {
        "c": "ﲈ",
        "l": "57:27:22",
        "a": "27",
        "s": "57"
      },
      {
        "c": "ﲉ",
        "l": "57:27:23",
        "a": "27",
        "s": "57"
      },
      {
        "c": "ﲊ",
        "l": "57:27:24",
        "a": "27",
        "s": "57"
      },
      {
        "c": "ﲋ",
        "l": "57:27:25",
        "a": "27",
        "s": "57"
      },
      {
        "c": "ﲌ",
        "l": "57:27:26",
        "a": "27",
        "s": "57"
      },
      {
        "c": "ﲍ",
        "l": "57:27:27",
        "a": "27",
        "s": "57"
      }
    ]
  },
  {
    "line": 10,
    "type": "ayah",
    "is_centered": false,
    "surah": "",
    "words": [
      {
        "c": "ﲎ",
        "l": "57:27:28",
        "a": "27",
        "s": "57"
      },
      {
        "c": "ﲏ",
        "l": "57:27:29",
        "a": "27",
        "s": "57"
      },
      {
        "c": "ﲐ",
        "l": "57:27:30",
        "a": "27",
        "s": "57"
      },
      {
        "c": "ﲑﲒ",
        "l": "57:27:31",
        "a": "27",
        "s": "57"
      },
      {
        "c": "ﲓ",
        "l": "57:27:32",
        "a": "27",
        "s": "57"
      },
      {
        "c": "ﲔ",
        "l": "57:27:33",
        "a": "27",
        "s": "57"
      },
      {
        "c": "ﲕ",
        "l": "57:27:34",
        "a": "27",
        "s": "57"
      },
      {
        "c": "ﲖ",
        "l": "57:27:35",
        "a": "27",
        "s": "57"
      },
      {
        "c": "ﲗﲘ",
        "l": "57:27:36",
        "a": "27",
        "s": "57"
      }
    ]
  },
  {
    "line": 11,
    "type": "ayah",
    "is_centered": false,
    "surah": "",
    "words": [
      {
        "c": "ﲙ",
        "l": "57:27:37",
        "a": "27",
        "s": "57"
      },
      {
        "c": "ﲚ",
        "l": "57:27:38",
        "a": "27",
        "s": "57"
      },
      {
        "c": "ﲛ",
        "l": "57:27:39",
        "a": "27",
        "s": "57"
      },
      {
        "c": "ﲜ",
        "l": "57:27:40",
        "a": "27",
        "s": "57"
      },
      {
        "c": "ﲝ",
        "l": "57:28:1",
        "a": "28",
        "s": "57"
      },
      {
        "c": "ﲞ",
        "l": "57:28:2",
        "a": "28",
        "s": "57"
      },
      {
        "c": "ﲟ",
        "l": "57:28:3",
        "a": "28",
        "s": "57"
      },
      {
        "c": "ﲠ",
        "l": "57:28:4",
        "a": "28",
        "s": "57"
      },
      {
        "c": "ﲡ",
        "l": "57:28:5",
        "a": "28",
        "s": "57"
      }
    ]
  },
  {
    "line": 12,
    "type": "ayah",
    "is_centered": false,
    "surah": "",
    "words": [
      {
        "c": "ﲢ",
        "l": "57:28:6",
        "a": "28",
        "s": "57"
      },
      {
        "c": "ﲣ",
        "l": "57:28:7",
        "a": "28",
        "s": "57"
      },
      {
        "c": "ﲤ",
        "l": "57:28:8",
        "a": "28",
        "s": "57"
      },
      {
        "c": "ﲥ",
        "l": "57:28:9",
        "a": "28",
        "s": "57"
      },
      {
        "c": "ﲦ",
        "l": "57:28:10",
        "a": "28",
        "s": "57"
      },
      {
        "c": "ﲧ",
        "l": "57:28:11",
        "a": "28",
        "s": "57"
      },
      {
        "c": "ﲨ",
        "l": "57:28:12",
        "a": "28",
        "s": "57"
      },
      {
        "c": "ﲩ",
        "l": "57:28:13",
        "a": "28",
        "s": "57"
      },
      {
        "c": "ﲪ",
        "l": "57:28:14",
        "a": "28",
        "s": "57"
      }
    ]
  },
  {
    "line": 13,
    "type": "ayah",
    "is_centered": false,
    "surah": "",
    "words": [
      {
        "c": "ﲫ",
        "l": "57:28:15",
        "a": "28",
        "s": "57"
      },
      {
        "c": "ﲬ",
        "l": "57:28:16",
        "a": "28",
        "s": "57"
      },
      {
        "c": "ﲭ",
        "l": "57:28:17",
        "a": "28",
        "s": "57"
      },
      {
        "c": "ﲮﲯ",
        "l": "57:28:18",
        "a": "28",
        "s": "57"
      },
      {
        "c": "ﲰ",
        "l": "57:28:19",
        "a": "28",
        "s": "57"
      },
      {
        "c": "ﲱ",
        "l": "57:28:20",
        "a": "28",
        "s": "57"
      },
      {
        "c": "ﲲ",
        "l": "57:28:21",
        "a": "28",
        "s": "57"
      },
      {
        "c": "ﲳ",
        "l": "57:28:22",
        "a": "28",
        "s": "57"
      },
      {
        "c": "ﲴ",
        "l": "57:29:1",
        "a": "29",
        "s": "57"
      },
      {
        "c": "ﲵ",
        "l": "57:29:2",
        "a": "29",
        "s": "57"
      }
    ]
  },
  {
    "line": 14,
    "type": "ayah",
    "is_centered": false,
    "surah": "",
    "words": [
      {
        "c": "ﲶ",
        "l": "57:29:3",
        "a": "29",
        "s": "57"
      },
      {
        "c": "ﲷ",
        "l": "57:29:4",
        "a": "29",
        "s": "57"
      },
      {
        "c": "ﲸ",
        "l": "57:29:5",
        "a": "29",
        "s": "57"
      },
      {
        "c": "ﲹ",
        "l": "57:29:6",
        "a": "29",
        "s": "57"
      },
      {
        "c": "ﲺ",
        "l": "57:29:7",
        "a": "29",
        "s": "57"
      },
      {
        "c": "ﲻ",
        "l": "57:29:8",
        "a": "29",
        "s": "57"
      },
      {
        "c": "ﲼ",
        "l": "57:29:9",
        "a": "29",
        "s": "57"
      },
      {
        "c": "ﲽ",
        "l": "57:29:10",
        "a": "29",
        "s": "57"
      },
      {
        "c": "ﲾ",
        "l": "57:29:11",
        "a": "29",
        "s": "57"
      },
      {
        "c": "ﲿ",
        "l": "57:29:12",
        "a": "29",
        "s": "57"
      }
    ]
  },
  {
    "line": 15,
    "type": "ayah",
    "is_centered": false,
    "surah": "",
    "words": [
      {
        "c": "ﳀ",
        "l": "57:29:13",
        "a": "29",
        "s": "57"
      },
      {
        "c": "ﳁ",
        "l": "57:29:14",
        "a": "29",
        "s": "57"
      },
      {
        "c": "ﳂ",
        "l": "57:29:15",
        "a": "29",
        "s": "57"
      },
      {
        "c": "ﳃ",
        "l": "57:29:16",
        "a": "29",
        "s": "57"
      },
      {
        "c": "ﳄ",
        "l": "57:29:17",
        "a": "29",
        "s": "57"
      },
      {
        "c": "ﳅﳆ",
        "l": "57:29:18",
        "a": "29",
        "s": "57"
      },
      {
        "c": "ﳇ",
        "l": "57:29:19",
        "a": "29",
        "s": "57"
      },
      {
        "c": "ﳈ",
        "l": "57:29:20",
        "a": "29",
        "s": "57"
      },
      {
        "c": "ﳉ",
        "l": "57:29:21",
        "a": "29",
        "s": "57"
      },
      {
        "c": "ﳊ",
        "l": "57:29:22",
        "a": "29",
        "s": "57"
      },
      {
        "c": "ﳋ",
        "l": "57:29:23",
        "a": "29",
        "s": "57"
      }
    ]
  }
]