[
  {
    "line": 1,
    "type": "ayah",
    "is_centered": false,
    "surah": "",
    "words": [
      {
        "c": "ﱁ",
        "l": "3:187:1",
        "a": "187",
        "s": "3"
      },
      {
        "c": "ﱂ",
        "l": "3:187:2",
        "a": "187",
        "s": "3"
      },
      {
        "c": "ﱃ",
        "l": "3:187:3",
        "a": "187",
        "s": "3"
      },
      {
        "c": "ﱄ",
        "l": "3:187:4",
        "a": "187",
        "s": "3"
      },
      {
        "c": "ﱅ",
        "l": "3:187:5",
        "a": "187",
        "s": "3"
      },
      {
        "c": "ﱆ",
        "l": "3:187:6",
        "a": "187",
        "s": "3"
      },
      {
        "c": "ﱇ",
        "l": "3:187:7",
        "a": "187",
        "s": "3"
      },
      {
        "c": "ﱈ",
        "l": "3:187:8",
        "a": "187",
        "s": "3"
      },
      {
        "c": "ﱉ",
        "l": "3:187:9",
        "a": "187",
        "s": "3"
      }
    ]
  },
  {
    "line": 2,
    "type": "ayah",
    "is_centered": false,
    "surah": "",
    "words": [
      {
        "c": "ﱊ",
        "l": "3:187:10",
        "a": "187",
        "s": "3"
      },
      {
        "c": "ﱋ",
        "l": "3:187:11",
        "a": "187",
        "s": "3"
      },
      {
        "c": "ﱌ",
        "l": "3:187:12",
        "a": "187",
        "s": "3"
      },
      {
        "c": "ﱍ",
        "l": "3:187:13",
        "a": "187",
        "s": "3"
      },
      {
        "c": "ﱎ",
        "l": "3:187:14",
        "a": "187",
        "s": "3"
      },
      {
        "c": "ﱏ",
        "l": "3:187:15",
        "a": "187",
        "s": "3"
      },
      {
        "c": "ﱐ",
        "l": "3:187:16",
        "a": "187",
        "s": "3"
      },
      {
        "c": "ﱑ",
        "l": "3:187:17",
        "a": "187",
        "s": "3"
      }
    ]
  },
  {
    "line": 3,
    "type": "ayah",
    "is_centered": false,
    "surah": "",
    "words": [
      {
        "c": "ﱒﱓ",
        "l": "3:187:18",
        "a": "187",
        "s": "3"
      },
      {
        "c": "ﱔ",
        "l": "3:187:19",
        "a": "187",
        "s": "3"
      },
      {
        "c": "ﱕ",
        "l": "3:187:20",
        "a": "187",
        "s": "3"
      },
      {
        "c": "ﱖ",
        "l": "3:187:21",
        "a": "187",
        "s": "3"
      },
      {
        "c": "ﱗ",
        "l": "3:187:22",
        "a": "187",
        "s": "3"
      },
      {
        "c": "ﱘ",
        "l": "3:188:1",
        "a": "188",
        "s": "3"
      },
      {
        "c": "ﱙ",
        "l": "3:188:2",
        "a": "188",
        "s": "3"
      },
      {
        "c": "ﱚ",
        "l": "3:188:3",
        "a": "188",
        "s": "3"
      },
      {
        "c": "ﱛ",
        "l": "3:188:4",
        "a": "188",
        "s": "3"
      },
      {
        "c": "ﱜ",
        "l": "3:188:5",
        "a": "188",
        "s": "3"
      }
    ]
  },
  {
    "line": 4,
    "type": "ayah",
    "is_centered": false,
    "surah": "",
    "words": [
      {
        "c": "ﱝ",
        "l": "3:188:6",
        "a": "188",
        "s": "3"
      },
      {
        "c": "ﱞ",
        "l": "3:188:7",
        "a": "188",
        "s": "3"
      },
      {
        "c": "ﱟ",
        "l": "3:188:8",
        "a": "188",
        "s": "3"
      },
      {
        "c": "ﱠ",
        "l": "3:188:9",
        "a": "188",
        "s": "3"
      },
      {
        "c": "ﱡ",
        "l": "3:188:10",
        "a": "188",
        "s": "3"
      },
      {
        "c": "ﱢ",
        "l": "3:188:11",
        "a": "188",
        "s": "3"
      },
      {
        "c": "ﱣ",
        "l": "3:188:12",
        "a": "188",
        "s": "3"
      },
      {
        "c": "ﱤ",
        "l": "3:188:13",
        "a": "188",
        "s": "3"
      },
      {
        "c": "ﱥ",
        "l": "3:188:14",
        "a": "188",
        "s": "3"
      }
    ]
  },
  {
    "line": 5,
    "type": "ayah",
    "is_centered": false,
    "surah": "",
    "words": [
      {
        "c": "ﱦ",
        "l": "3:188:15",
        "a": "188",
        "s": "3"
      },
      {
        "c": "ﱧ",
        "l": "3:188:16",
        "a": "188",
        "s": "3"
      },
      {
        "c": "ﱨﱩ",
        "l": "3:188:17",
        "a": "188",
        "s": "3"
      },
      {
        "c": "ﱪ",
        "l": "3:188:18",
        "a": "188",
        "s": "3"
      },
      {
        "c": "ﱫ",
        "l": "3:188:19",
        "a": "188",
        "s": "3"
      },
      {
        "c": "ﱬ",
        "l": "3:188:20",
        "a": "188",
        "s": "3"
      },
      {
        "c": "ﱭ",
        "l": "3:188:21",
        "a": "188",
        "s": "3"
      },
      {
        "c": "ﱮ",
        "l": "3:189:1",
        "a": "189",
        "s": "3"
      },
      {
        "c": "ﱯ",
        "l": "3:189:2",
        "a": "189",
        "s": "3"
      }
    ]
  },
  {
    "line": 6,
    "type": "ayah",
    "is_centered": false,
    "surah": "",
    "words": [
      {
        "c": "ﱰ",
        "l": "3:189:3",
        "a": "189",
        "s": "3"
      },
      {
        "c": "ﱱﱲ",
        "l": "3:189:4",
        "a": "189",
        "s": "3"
      },
      {
        "c": "ﱳ",
        "l": "3:189:5",
        "a": "189",
        "s": "3"
      },
      {
        "c": "ﱴ",
        "l": "3:189:6",
        "a": "189",
        "s": "3"
      },
      {
        "c": "ﱵ",
        "l": "3:189:7",
        "a": "189",
        "s": "3"
      },
      {
        "c": "ﱶ",
        "l": "3:189:8",
        "a": "189",
        "s": "3"
      },
      {
        "c": "ﱷ",
        "l": "3:189:9",
        "a": "189",
        "s": "3"
      },
      {
        "c": "ﱸ",
        "l": "3:189:10",
        "a": "189",
        "s": "3"
      },
      {
        "c": "ﱹ",
        "l": "3:190:1",
        "a": "190",
        "s": "3"
      },
      {
        "c": "ﱺ",
        "l": "3:190:2",
        "a": "190",
        "s": "3"
      }
    ]
  },
  {
    "line": 7,
    "type": "ayah",
    "is_centered": false,
    "surah": "",
    "words": [
      {
        "c": "ﱻ",
        "l": "3:190:3",
        "a": "190",
        "s": "3"
      },
      {
        "c": "ﱼ",
        "l": "3:190:4",
        "a": "190",
        "s": "3"
      },
      {
        "c": "ﱽ",
        "l": "3:190:5",
        "a": "190",
        "s": "3"
      },
      {
        "c": "ﱾ",
        "l": "3:190:6",
        "a": "190",
        "s": "3"
      },
      {
        "c": "ﱿ",
        "l": "3:190:7",
        "a": "190",
        "s": "3"
      },
      {
        "c": "ﲀ",
        "l": "3:190:8",
        "a": "190",
        "s": "3"
      },
      {
        "c": "ﲁ",
        "l": "3:190:9",
        "a": "190",
        "s": "3"
      }
    ]
  },
  {
    "line": 8,
    "type": "ayah",
    "is_centered": false,
    "surah": "",
    "words": [
      {
        "c": "ﲂ",
        "l": "3:190:10",
        "a": "190",
        "s": "3"
      },
      {
        "c": "ﲃ",
        "l": "3:190:11",
        "a": "190",
        "s": "3"
      },
      {
        "c": "ﲄ",
        "l": "3:190:12",
        "a": "190",
        "s": "3"
      },
      {
        "c": "ﲅ",
        "l": "3:191:1",
        "a": "191",
        "s": "3"
      },
      {
        "c": "ﲆ",
        "l": "3:191:2",
        "a": "191",
        "s": "3"
      },
      {
        "c": "ﲇ",
        "l": "3:191:3",
        "a": "191",
        "s": "3"
      },
      {
        "c": "ﲈ",
        "l": "3:191:4",
        "a": "191",
        "s": "3"
      },
      {
        "c": "ﲉ",
        "l": "3:191:5",
        "a": "191",
        "s": "3"
      }
    ]
  },
  {
    "line": 9,
    "type": "ayah",
    "is_centered": false,
    "surah": "",
    "words": [
      {
        "c": "ﲊ",
        "l": "3:191:6",
        "a": "191",
        "s": "3"
      },
      {
        "c": "ﲋ",
        "l": "3:191:7",
        "a": "191",
        "s": "3"
      },
      {
        "c": "ﲌ",
        "l": "3:191:8",
        "a": "191",
        "s": "3"
      },
      {
        "c": "ﲍ",
        "l": "3:191:9",
        "a": "191",
        "s": "3"
      },
      {
        "c": "ﲎ",
        "l": "3:191:10",
        "a": "191",
        "s": "3"
      },
      {
        "c": "ﲏ",
        "l": "3:191:11",
        "a": "191",
        "s": "3"
      },
      {
        "c": "ﲐ",
        "l": "3:191:12",
        "a": "191",
        "s": "3"
      }
    ]
  },
  {
    "line": 10,
    "type": "ayah",
    "is_centered": false,
    "surah": "",
    "words": [
      {
        "c": "ﲑ",
        "l": "3:191:13",
        "a": "191",
        "s": "3"
      },
      {
        "c": "ﲒ",
        "l": "3:191:14",
        "a": "191",
        "s": "3"
      },
      {
        "c": "ﲓ",
        "l": "3:191:15",
        "a": "191",
        "s": "3"
      },
      {
        "c": "ﲔ",
        "l": "3:191:16",
        "a": "191",
        "s": "3"
      },
      {
        "c": "ﲕ",
        "l": "3:191:17",
        "a": "191",
        "s": "3"
      },
      {
        "c": "ﲖ",
        "l": "3:191:18",
        "a": "191",
        "s": "3"
      },
      {
        "c": "ﲗ",
        "l": "3:191:19",
        "a": "191",
        "s": "3"
      },
      {
        "c": "ﲘ",
        "l": "3:191:20",
        "a": "191",
        "s": "3"
      },
      {
        "c": "ﲙ",
        "l": "3:191:21",
        "a": "191",
        "s": "3"
      },
      {
        "c": "ﲚ",
        "l": "3:191:22",
        "a": "191",
        "s": "3"
      }
    ]
  },
  {
    "line": 11,
    "type": "ayah",
    "is_centered": false,
    "surah": "",
    "words": [
      {
        "c": "ﲛ",
        "l": "3:192:1",
        "a": "192",
        "s": "3"
      },
      {
        "c": "ﲜ",
        "l": "3:192:2",
        "a": "192",
        "s": "3"
      },
      {
        "c": "ﲝ",
        "l": "3:192:3",
        "a": "192",
        "s": "3"
      },
      {
        "c": "ﲞ",
        "l": "3:192:4",
        "a": "192",
        "s": "3"
      },
      {
        "c": "ﲟ",
        "l": "3:192:5",
        "a": "192",
        "s": "3"
      },
      {
        "c": "ﲠ",
        "l": "3:192:6",
        "a": "192",
        "s": "3"
      },
      {
        "c": "ﲡﲢ",
        "l": "3:192:7",
        "a": "192",
        "s": "3"
      },
      {
        "c": "ﲣ",
        "l": "3:192:8",
        "a": "192",
        "s": "3"
      },
      {
        "c": "ﲤ",
        "l": "3:192:9",
        "a": "192",
        "s": "3"
      },
      {
        "c": "ﲥ",
        "l": "3:192:10",
        "a": "192",
        "s": "3"
      }
    ]
  },
  {
    "line": 12,
    "type": "ayah",
    "is_centered": false,
    "surah": "",
    "words": [
      {
        "c": "ﲦ",
        "l": "3:192:11",
        "a": "192",
        "s": "3"
      },
      {
        "c": "ﲧ",
        "l": "3:192:12",
        "a": "192",
        "s": "3"
      },
      {
        "c": "ﲨ",
        "l": "3:193:1",
        "a": "193",
        "s": "3"
      },
      {
        "c": "ﲩ",
        "l": "3:193:2",
        "a": "193",
        "s": "3"
      },
      {
        "c": "ﲪ",
        "l": "3:193:3",
        "a": "193",
        "s": "3"
      },
      {
        "c": "ﲫ",
        "l": "3:193:4",
        "a": "193",
        "s": "3"
      },
      {
        "c": "ﲬ",
        "l": "3:193:5",
        "a": "193",
        "s": "3"
      },
      {
        "c": "ﲭ",
        "l": "3:193:6",
        "a": "193",
        "s": "3"
      },
      {
        "c": "ﲮ",
        "l": "3:193:7",
        "a": "193",
        "s": "3"
      }
    ]
  },
  {
    "line": 13,
    "type": "ayah",
    "is_centered": false,
    "surah": "",
    "words": [
      {
        "c": "ﲯ",
        "l": "3:193:8",
        "a": "193",
        "s": "3"
      },
      {
        "c": "ﲰ",
        "l": "3:193:9",
        "a": "193",
        "s": "3"
      },
      {
        "c": "ﲱﲲ",
        "l": "3:193:10",
        "a": "193",
        "s": "3"
      },
      {
        "c": "ﲳ",
        "l": "3:193:11",
        "a": "193",
        "s": "3"
      },
      {
        "c": "ﲴ",
        "l": "3:193:12",
        "a": "193",
        "s": "3"
      },
      {
        "c": "ﲵ",
        "l": "3:193:13",
        "a": "193",
        "s": "3"
      },
      {
        "c": "ﲶ",
        "l": "3:193:14",
        "a": "193",
        "s": "3"
      },
      {
        "c": "ﲷ",
        "l": "3:193:15",
        "a": "193",
        "s": "3"
      },
      {
        "c": "ﲸ",
        "l": "3:193:16",
        "a": "193",
        "s": "3"
      }
    ]
  },
  {
    "line": 14,
    "type": "ayah",
    "is_centered": false,
    "surah": "",
    "words": [
      {
        "c": "ﲹ",
        "l": "3:193:17",
        "a": "193",
        "s": "3"
      },
      {
        "c": "ﲺ",
        "l": "3:193:18",
        "a": "193",
        "s": "3"
      },
      {
        "c": "ﲻ",
        "l": "3:193:19",
        "a": "193",
        "s": "3"
      },
      {
        "c": "ﲼ",
        "l": "3:193:20",
        "a": "193",
        "s": "3"
      },
      {
        "c": "ﲽ",
        "l": "3:193:21",
        "a": "193",
        "s": "3"
      },
      {
        "c": "ﲾ",
        "l": "3:194:1",
        "a": "194",
        "s": "3"
      },
      {
        "c": "ﲿ",
        "l": "3:194:2",
        "a": "194",
        "s": "3"
      },
      {
        "c": "ﳀ",
        "l": "3:194:3",
        "a": "194",
        "s": "3"
      },
      {
        "c": "ﳁ",
        "l": "3:194:4",
        "a": "194",
        "s": "3"
      },
      {
        "c": "ﳂ",
        "l": "3:194:5",
        "a": "194",
        "s": "3"
      }
    ]
  },
  {
    "line": 15,
    "type": "ayah",
    "is_centered": false,
    "surah": "",
    "words": [
      {
        "c": "ﳃ",
        "l": "3:194:6",
        "a": "194",
        "s": "3"
      },
      {
        "c": "ﳄ",
        "l": "3:194:7",
        "a": "194",
        "s": "3"
      },
      {
        "c": "ﳅ",
        "l": "3:194:8",
        "a": "194",
        "s": "3"
      },
      {
        "c": "ﳆ",
        "l": "3:194:9",
        "a": "194",
        "s": "3"
      },
      {
        "c": "ﳇﳈ",
        "l": "3:194:10",
        "a": "194",
        "s": "3"
      },
      {
        "c": "ﳉ",
        "l": "3:194:11",
        "a": "194",
        "s": "3"
      },
      {
        "c": "ﳊ",
        "l": "3:194:12",
        "a": "194",
        "s": "3"
      },
      {
        "c": "ﳋ",
        "l": "3:194:13",
        "a": "194",
        "s": "3"
      },
      {
        "c": "ﳌ",
        "l": "3:194:14",
        "a": "194",
        "s": "3"
      },
      {
        "c": "ﳍ",
        "l": "3:194:15",
        "a": "194",
        "s": "3"
      }
    ]
  }
]